micropython_shtc3/__init__.py
micropython_shtc3/i2c_helpers.py
micropython_shtc3/shtc3.py
micropython_shtc3-0.1.0.dist-info/LICENSE
micropython_shtc3-0.1.0.dist-info/METADATA
micropython_shtc3-0.1.0.dist-info/WHEEL
micropython_shtc3-0.1.0.dist-info/top_level.txt
micropython_shtc3-0.1.0.dist-info/RECORD
