Metadata-Version: 2.1
Name: micropython-shtc3
Version: 0.1.0
Summary: MicroPython Driver for the Sensirion SHTC3 Temperature and Humidity Sensor
Author-email: JDM <xxyx@mailmeto.mozmail.com>
License: MIT
Project-URL: Homepage, https://github.com/jposada202020/MicroPython_SHTC3
Keywords: sensor,micropython,shtc3,micropython,driver,sensor,shtc3,sensirion,humidity,temperature
Classifier: Intended Audience :: Developers
Classifier: Topic :: Software Development :: Libraries
Classifier: Topic :: Software Development :: Embedded Systems
Classifier: Topic :: System :: Hardware
Classifier: License :: OSI Approved :: MIT License
Classifier: Programming Language :: Python :: Implementation :: MicroPython
License-File: LICENSE
